pytest_object_getter/__init__.py
pytest_object_getter/fixtures.py
pytest_object_getter/py.typed
pytest_object_getter-1.0.2.dist-info/LICENSE
pytest_object_getter-1.0.2.dist-info/METADATA
pytest_object_getter-1.0.2.dist-info/WHEEL
pytest_object_getter-1.0.2.dist-info/entry_points.txt
pytest_object_getter-1.0.2.dist-info/top_level.txt
pytest_object_getter-1.0.2.dist-info/RECORD
